pyConfObj/__init__.py
pyConfObj/config.py
pyconfobj-0.1.5.dist-info/METADATA
pyconfobj-0.1.5.dist-info/WHEEL
pyconfobj-0.1.5.dist-info/licenses/LICENSE
pyconfobj-0.1.5.dist-info/RECORD
