Metadata-Version: 2.1
Name: pyConfObj
Version: 0.1.5
Summary: A way to define configuration files through classes, save it and load configuration from json/yaml
Project-URL: Homepage, https://github.com/otger/pyConfObject
Project-URL: Bug Tracker, https://github.com/otger/pyConfObject/issues
Author-email: Otger Ballester <otger@ifae.es>
License-File: LICENSE
Classifier: License :: OSI Approved :: MIT License
Classifier: Operating System :: OS Independent
Classifier: Programming Language :: Python :: 3
Requires-Python: >=3.7
